subgrapy/__init__.py
subgrapy/data_io/__init__.py
subgrapy/data_io/data_io.py
subgrapy/data_io/subgraphs.py
subgrapy/data_io/tests/__init__.py
subgrapy/data_io/tests/test_data_io.py
subgrapy/instrumentation/__init__.py
subgrapy/instrumentation/instrumentation.py
subgrapy/maths/__init__.py
subgrapy/maths/maths.py
subgrapy/maths/tests/__init__.py
subgrapy/maths/tests/test_maths.py
subgrapy/utils/__init__.py
subgrapy/utils/dates.py
subgrapy/utils/tests/__init__.py
subgrapy/utils/tests/test_dates.py
subgrapy-1.0.0a1.dist-info/LICENSE
subgrapy-1.0.0a1.dist-info/METADATA
subgrapy-1.0.0a1.dist-info/WHEEL
subgrapy-1.0.0a1.dist-info/top_level.txt
subgrapy-1.0.0a1.dist-info/RECORD
