Metadata-Version: 2.1
Name: subgrapy
Version: 1.0.0a1
Summary: subgrapy is a library that handles data I/O, aggregation, and modeling for The Graphs subgraphs.
Home-page: https://github.com/bordumb/grapy
Maintainer: bordumb
License: Apache License, Version 2.0
Platform: UNKNOWN
Classifier: Programming Language :: Python
Classifier: Programming Language :: Python :: 3.6
Classifier: Intended Audience :: Science/Research
Classifier: Topic :: Scientific/Engineering
Classifier: Topic :: Scientific/Engineering :: Mathematics
Classifier: Operating System :: OS Independent
Classifier: Intended Audience :: Financial and Insurance Industry
Classifier: Intended Audience :: Information Technology
